MANIFEST.in
README.rst
fluidinfo.py
setup.py
fluidinfo.py.egg-info/PKG-INFO
fluidinfo.py.egg-info/SOURCES.txt
fluidinfo.py.egg-info/dependency_links.txt
fluidinfo.py.egg-info/requires.txt
fluidinfo.py.egg-info/top_level.txt