Metadata-Version: 1.0
Name: fluidinfo.py
Version: 1.2.0
Summary: A thin wrapper for Fluidinfo's RESTful API
Home-page: http://fluidinfo.com
Author: Nicholas Tollervey (based upon work by Sanghyeon Seo)
Author-email: ntoll@ntoll.org
License: MIT
Platform: UNKNOWN
Classifier: Development Status :: 4 - Beta
Classifier: Environment :: Web Environment
Classifier: Intended Audience :: Developers
Classifier: License :: OSI Approved :: MIT License
Classifier: Operating System :: OS Independent
Classifier: Programming Language :: Python
Classifier: Topic :: Database
Classifier: Topic :: Internet :: WWW/HTTP
Classifier: Topic :: Software Development :: Libraries
